parse_llm_code/__init__.py
parse_llm_code/extract_code.py
tests/__init__.py
tests/test_extract_codes.py
tests/test_extract_first_code.py
parse_llm_code-0.1.31.dist-info/LICENSE
parse_llm_code-0.1.31.dist-info/METADATA
parse_llm_code-0.1.31.dist-info/WHEEL
parse_llm_code-0.1.31.dist-info/top_level.txt
parse_llm_code-0.1.31.dist-info/RECORD
