Metadata-Version: 2.1
Name: parse_llm_code
Version: 0.1.31
Summary: a lib to parse llm answer to code
Home-page: https://github.com/aboutmydreams/parse_llm_code
Author: aboutmydreams
Author-email: aboutmydreams@163.com
Classifier: Programming Language :: Python :: 3
Classifier: License :: OSI Approved :: MIT License
Classifier: Operating System :: OS Independent
License-File: LICENSE
